openelectricity/__init__.py
openelectricity/client.py
openelectricity/logging.py
openelectricity/settings_schema.py
openelectricity/styles.py
openelectricity/types.py
openelectricity/models/__init__.py
openelectricity/models/base.py
openelectricity/models/facilities.py
openelectricity/models/field_types.py
openelectricity/models/networks.py
openelectricity/models/timeseries.py
openelectricity/models/units.py
openelectricity/models/user.py
openelectricity-0.9.2.dist-info/METADATA
openelectricity-0.9.2.dist-info/WHEEL
openelectricity-0.9.2.dist-info/licenses/LICENSE
openelectricity-0.9.2.dist-info/RECORD
