Metadata-Version: 2.4
Name: openelectricity
Version: 0.9.2
Summary: OpenElectricity Python Client
Author-email: Nik Cubrilovic <git@nikcub.me>
License: MIT
License-File: LICENSE
Classifier: Development Status :: 4 - Beta
Classifier: Intended Audience :: Developers
Classifier: Programming Language :: Python :: 3
Classifier: Programming Language :: Python :: 3.10
Classifier: Programming Language :: Python :: 3.11
Classifier: Programming Language :: Python :: 3.12
Classifier: Topic :: Software Development :: Libraries :: Python Modules
Requires-Python: >=3.10
Requires-Dist: aiohttp[speedups]>=3.11.12
Requires-Dist: pydantic-settings>=2.7.1
Requires-Dist: pydantic>=2.10.3
Provides-Extra: analysis
Requires-Dist: polars>=0.20.5; extra == 'analysis'
Requires-Dist: pyarrow>=15.0.0; extra == 'analysis'
Requires-Dist: rich>=13.7.0; extra == 'analysis'
Provides-Extra: dev
Requires-Dist: build>=1.0.3; extra == 'dev'
Requires-Dist: pytest-asyncio>=0.23.0; extra == 'dev'
Requires-Dist: pytest-cov>=4.1.0; extra == 'dev'
Requires-Dist: pytest>=8.0.0; extra == 'dev'
Requires-Dist: ruff>=0.8.3; extra == 'dev'
